gardena_smart/__init__.py
gardena_smart-0.2.dist-info/LICENSE.txt
gardena_smart-0.2.dist-info/METADATA
gardena_smart-0.2.dist-info/RECORD
gardena_smart-0.2.dist-info/WHEEL
gardena_smart-0.2.dist-info/top_level.txt
