Metadata-Version: 2.1
Name: gardena-smart
Version: 0.2
Summary: Library to access the gardena smart platform
Home-page: http://github.com/rcastberg/gardena_smart
Author: Rene Castberg
Author-email: rene@castberg.org
License: GPL
Platform: UNKNOWN
